MANIFEST.in
requirements.txt
setup.py
matest/__init__.py
matest/a111.py
matest/a15.py
matest/core.py
matest/main.py
matest.egg-info/PKG-INFO
matest.egg-info/SOURCES.txt
matest.egg-info/dependency_links.txt
matest.egg-info/requires.txt
matest.egg-info/top_level.txt
matest/conf/matest.json
matest/conf/mpost.json
matest/conf/mvlog.json
matest/conf/mwebui.json
matest/conf/post.html.json
matest/plugins/__init__.py
matest/plugins/mdb.py
matest/plugins/mpost.py
matest/plugins/mvlog.py
matest/plugins/mwebui.py