Metadata-Version: 2.1
Name: matest
Version: 0.0.8
Summary: mate test
Home-page: https://github.com/matest
Author: matest
Author-email: erenjian@qq.com
License: MIT Licence
Keywords: mate,test,matest
Platform: any
